[
  {
    "name": "clapp-store",
    "version": "1.0.0",
    "language": "python",
    "description": "Clapp paket yöneticisinin grafiksel kullanıcı arayüzü",
    "entry": "main.py",
    "dependencies": [
      "flet",
      "requests"
    ],
    "folder": "clapp-store",
    "repo_url": "https://github.com/mburakmmm/clapp-packages",
    "subdir": "clapp-store"
  },
  {
    "name": "cloud-calc",
    "version": "1.0.0",
    "language": "python",
    "description": "Modern ve profesyonel hesap makinesi uygulaması",
    "entry": "main.py",
    "dependencies": [],
    "folder": "cloud-calc",
    "repo_url": "https://github.com/mburakmmm/clapp-packages",
    "subdir": "cloud-calc"
  },
  {
    "name": "cloud-finder",
    "version": "1.0.1",
    "language": "python",
    "description": "MacOS Finder'a benzeyen modern dosya gezgini",
    "entry": "main.py",
    "dependencies": [
      "flet>=0.28.0",
      "pathlib"
    ],
    "folder": "cloud-finder",
    "repo_url": "https://github.com/mburakmmm/clapp-packages",
    "subdir": "cloud-finder"
  },
  {
    "name": "cloud-notepad",
    "version": "1.0.0",
    "language": "python",
    "description": "Modern ve gelişmiş cloud destekli notepad uygulaması. PyQt6 ile geliştirilmiş, syntax highlighting, tema desteği, çoklu sekme ve cloud senkronizasyon özellikleri ile Notepad++ benzeri deneyim sunar.",
    "entry": "main.py",
    "dependencies": [
      "PyQt6==6.6.1",
      "PyQt6-Qt6==6.6.1",
      "PyQt6-sip==13.6.0",
      "pygments==2.17.2",
      "requests==2.31.0",
      "cryptography==41.0.8"
    ],
    "folder": "cloud-notepad",
    "repo_url": "https://github.com/mburakmmm/clapp-packages",
    "subdir": "cloud-notepad"
  },
  {
    "name": "cloud-system",
    "version": "1.0.0",
    "language": "python",
    "description": "Modern sistem yöneticisi ve görev yöneticisi uygulaması",
    "entry": "main.py",
    "dependencies": [
      "flet",
      "psutil"
    ],
    "folder": "cloud-system",
    "repo_url": "https://github.com/mburakmmm/clapp-packages",
    "subdir": "cloud-system"
  },
  {
    "name": "cloud-web-browser",
    "version": "1.0.0",
    "language": "python",
    "description": "Modern ve hızlı web tarayıcı uygulaması. Python ve Flet framework'ü ile geliştirilmiştir. WebView teknolojisi ile gerçek web sayfalarını uygulama içinde görüntüler.",
    "entry": "cloud_browser.py",
    "dependencies": [
      "flet>=0.21.0",
      "flet-webview>=0.1.0",
      "requests>=2.31.0",
      "beautifulsoup4>=4.12.0"
    ],
    "folder": "cloud-web-browser",
    "repo_url": "https://github.com/mburakmmm/clapp-packages",
    "subdir": "cloud-web-browser"
  },
  {
    "name": "pycloud-os",
    "version": "1.0.0",
    "language": "python",
    "description": "Modern, Python tabanlı, macOS benzeri işletim sistemi. Modüler mimarisi, güçlü GUI sistemi ve kapsamlı uygulama ekosistemine sahiptir.",
    "entry": "main.py",
    "dependencies": [
      "PyQt6",
      "PyQt6-WebEngine",
      "Pillow",
      "psutil",
      "requests",
      "pyserial",
      "Flask",
      "pytest",
      "pytest-cov",
      "pytest-mock",
      "black",
      "flake8",
      "isort",
      "mypy",
      "types-requests",
      "types-setuptools",
      "sphinx",
      "sphinx-rtd-theme",
      "sphinx-autodoc-typehints",
      "wheel",
      "setuptools",
      "build",
      "ipython",
      "jupyterlab",
      "memory-profiler",
      "line-profiler",
      "bandit",
      "safety",
      "pre-commit"
    ],
    "folder": "pycloud-os",
    "repo_url": "https://github.com/mburakmmm/clapp-packages",
    "subdir": "pycloud-os"
  }
]